.DS_Store
quicksand/__init__.py
quicksand/quicksand.py
quicksand/quicksand_exe.yara
quicksand/quicksand_exploits.yara
quicksand/quicksand_pdf.yara
quicksand-2.1.1.data/scripts/quicksand
quicksand-2.1.1.dist-info/licenses/LICENSE
quicksand-2.1.1.dist-info/METADATA
quicksand-2.1.1.dist-info/WHEEL
quicksand-2.1.1.dist-info/top_level.txt
quicksand-2.1.1.dist-info/RECORD
