Metadata-Version: 2.4
Name: quicksand
Version: 2.1.1
Summary: QuickSand is a module to scan streams inside documents with Yara
Home-page: https://github.com/tylabs/quicksand
Download-URL: https://github.com/tylabs/quicksand/archive/refs/tags/2.1.1.tar.gz
Author: tylabs.com
Author-email: nospam@tylabs.com
Project-URL: Bug Tracker, https://github.com/tylabs/quicksand/issues
Keywords: document,malware,forensics,yara,parser
Classifier: Programming Language :: Python :: 3
Classifier: License :: OSI Approved :: MIT License
Classifier: Operating System :: OS Independent
Requires-Python: >=3.6
License-File: LICENSE
Requires-Dist: pdfreader
Requires-Dist: oletools
Requires-Dist: cryptography
Requires-Dist: zipfile38
Requires-Dist: msoffcrypto-tool
Requires-Dist: olefile
Requires-Dist: yara-python>=4.3.0
Dynamic: author
Dynamic: author-email
Dynamic: classifier
Dynamic: description
Dynamic: description-content-type
Dynamic: download-url
Dynamic: home-page
Dynamic: keywords
Dynamic: license-file
Dynamic: project-url
Dynamic: requires-dist
Dynamic: requires-python
Dynamic: summary
